{"type":"FeatureCollection","metadata":{"name":"Jaluse","creator":"Yandex Map Constructor"},"features":[{"type":"Feature","id":0,"geometry":{"coordinates":[25.127073,54.647203],"type":"Point"},"properties":{"description":"Литва, Вильнюс, улица Лентварё","iconCaption":"Vilnius Lentvario gatvė 3","marker-color":"#1e98ff"}},{"type":"Feature","id":1,"geometry":{"coordinates":[23.94728,54.870311],"type":"Point"},"properties":{"description":"Литва, Каунасский уезд, Каунас, улица Дробес","marker-color":"#1e98ff"}},{"type":"Feature","id":2,"geometry":{"coordinates":[24.368859,55.721245],"type":"Point"},"properties":{"description":"Литва, Паневежский уезд, Самоуправление города Паневежиса, Паневежис, J. Basanavičiaus gatvė","marker-color":"#1e98ff"}},{"type":"Feature","id":3,"geometry":{"coordinates":[23.315342,55.954062],"type":"Point"},"properties":{"description":"Литва, Шяуляйский уезд, Шяулиу место савивалдибе, город Шяуляй, J. Basanavičiaus gatvė","marker-color":"#1e98ff"}},{"type":"Feature","id":4,"geometry":{"coordinates":[21.151453,55.754471],"type":"Point"},"properties":{"description":"Литва, Клайпедский уезд, Клайпедское городское самоуправление, Клайпеда, Akmenų gatvė, 3","marker-color":"#1e98ff"}}]}